h2o_wave/__init__.py
h2o_wave/__main__.py
h2o_wave/cli.py
h2o_wave/core.py
h2o_wave/db.py
h2o_wave/graphics.py
h2o_wave/ide.py
h2o_wave/metadata.py
h2o_wave/py.typed
h2o_wave/routing.py
h2o_wave/server.py
h2o_wave/share.py
h2o_wave/test.py
h2o_wave/types.py
h2o_wave/ui.py
h2o_wave/ui_ext.py
h2o_wave/version.py
h2o_wave-1.7.7.dist-info/METADATA
h2o_wave-1.7.7.dist-info/WHEEL
h2o_wave-1.7.7.dist-info/entry_points.txt
h2o_wave-1.7.7.dist-info/licenses/LICENSE
h2o_wave-1.7.7.dist-info/RECORD
