Metadata-Version: 2.4
Name: h2o-wave
Version: 1.7.7
Summary: Python driver for H2O Wave Realtime Apps
Project-URL: Homepage, https://wave.h2o.ai/
Project-URL: Documentation, https://wave.h2o.ai/
Project-URL: Repository, https://github.com/h2oai/wave
Project-URL: Changelog, https://github.com/h2oai/wave/releases
Author-email: Prithvi Prabhu <prithvi@h2o.ai>
Maintainer-email: Martin Turoci <martin.turoci@h2o.ai>, Marek Mihok <marek.mihok@h2o.ai>
License-Expression: Apache-2.0
License-File: LICENSE
Keywords: Data Science,Low code,Machine Learning,Realtime,UI
Classifier: Development Status :: 5 - Production/Stable
Classifier: Intended Audience :: Developers
Classifier: License :: OSI Approved :: Apache Software License
Classifier: Operating System :: OS Independent
Classifier: Programming Language :: Python :: 3
Classifier: Programming Language :: Python :: 3.8
Classifier: Programming Language :: Python :: 3.9
Classifier: Programming Language :: Python :: 3.10
Classifier: Programming Language :: Python :: 3.11
Classifier: Topic :: Communications :: Chat
Classifier: Topic :: Internet :: WWW/HTTP :: Dynamic Content
Classifier: Topic :: Scientific/Engineering :: Visualization
Classifier: Topic :: Software Development :: Libraries :: Application Frameworks
Classifier: Topic :: Software Development :: Widget Sets
Classifier: Topic :: System :: Distributed Computing
Requires-Python: >=3.8
Requires-Dist: click
Requires-Dist: httpx>=0.16.1
Requires-Dist: inquirer
Requires-Dist: starlette>=0.13.8
Requires-Dist: uvicorn>=0.17.6
